getsynthpy-0.2.1.data/scripts/synthpy
synthpy/__init__.py
synthpy/__main__.py
synthpy/exceptions.py
synthpy/model.py
synthpy/client/__init__.py
synthpy/client/augmentation.py
synthpy/client/encoder.py
synthpy/client/generate.py
synthpy/client/ingest.py
synthpy/client/namespace.py
synthpy/client/override.py
synthpy/client/transport.py
synthpy/client/utils.py
getsynthpy-0.2.1.dist-info/LICENSE
getsynthpy-0.2.1.dist-info/METADATA
getsynthpy-0.2.1.dist-info/WHEEL
getsynthpy-0.2.1.dist-info/top_level.txt
getsynthpy-0.2.1.dist-info/RECORD
