Metadata-Version: 2.1
Name: getsynthpy
Version: 0.2.1
Summary: A Python-native synthd client library
Home-page: UNKNOWN
Author: Damien Broka
Author-email: damien@getsynth.com
License: UNKNOWN
Platform: UNKNOWN
Requires-Python: >=3.7
Requires-Dist: setuptools
Requires-Dist: aiohttp (<4.1.0,>=3.6.2)
Requires-Dist: yarl (<1.7.0,>=1.4.2)
Requires-Dist: click (<8.0,>=7.0)
Requires-Dist: colored (<1.5.0,>=1.4.2)
Requires-Dist: coloredlogs (<16.0,>=10.0)
